dstemplatest/__init__.py
dstemplatest/constants.py
dstemplatest/structure.py
dstemplatest-0.0.17.dist-info/METADATA
dstemplatest-0.0.17.dist-info/WHEEL
dstemplatest-0.0.17.dist-info/entry_points.txt
dstemplatest-0.0.17.dist-info/top_level.txt
dstemplatest-0.0.17.dist-info/RECORD
