Metadata-Version: 2.1
Name: dstemplatest
Version: 0.0.17
Summary: A Python package for creating project structure.
Home-page: https://github.com/ravi46931/dstemplatest-pypi
Author: ravi46931
Author-email: ravikumar46931@gmail.com
Project-URL: Bug Tracker, https://github.com/ravi46931/dstemplatest-pypi/issues
Requires-Dist: pandas
Requires-Dist: numpy
Requires-Dist: requests
